{
  "generator-jhipster": {
    "applicationType": "monolith",
    "gitCompany": "",
    "baseName": "timesuponline",
    "packageName": "com.letotoche.timesuponline",
    "packageFolder": "com/letotoche/timesuponline",
    "serverPort": 8080,
    "serviceDiscoveryType": false,
    "authenticationType": "jwt",
    "uaaBaseName": "../uaa",
    "cacheProvider": "ehcache",
    "enableHibernateCache": true,
    "websocket": false,
    "databaseType": "sql",
    "devDatabaseType": "h2Disk",
    "prodDatabaseType": "postgresql",
    "searchEngine": false,
    "enableSwaggerCodegen": false,
    "messageBroker": false,
    "buildTool": "maven",
    "useSass": true,
    "clientPackageManager": "npm",
    "testFrameworks": ["protractor"],
    "enableTranslation": true,
    "nativeLanguage": "fr",
    "languages": ["en", "fr"],
    "clientFramework": "angularX",
    "jhiPrefix": "jhi",
    "jhipsterVersion": "6.8.0",
    "jwtSecretKey": "MTFmNDMwZGJkOTY0MWRkZWE1N2MwMTdlMDFiMmZkYjRmODkxODRlYmI2YTBmZjYyOThkNWY0ZDJiMGE4ZjE0ZGIyZDU5NjcyNjczNzA1ZDgwZTIxZDFkNzE1MmMwMDkwOWFhOTcwZWIyM2IyNzVmY2VkZTViZTZlMTUzMzRkMjE=",
    "embeddableLaunchScript": false,
    "clientTheme": "none",
    "creationTimestamp": 1588949236844,
    "entitySuffix": "",
    "dtoSuffix": "DTO",
    "otherModules": [],
    "blueprints": []
  },
  "git-provider": "GitHub",
  "git-company": "Letotoche",
  "repository-name": "timesuponline"
}
